mwdstdb/__init__.py
mwdstdb/api/__init__.py
mwdstdb/api/auth.py
mwdstdb/api/borehole.py
mwdstdb/api/client.py
mwdstdb/api/control.py
mwdstdb/api/core.py
mwdstdb/api/deps/actrl.py
mwdstdb/api/deps/auth.py
mwdstdb/api/deps/exists.py
mwdstdb/api/deps/units.py
mwdstdb/api/deps/utils.py
mwdstdb/api/events.py
mwdstdb/api/export.py
mwdstdb/api/lists.py
mwdstdb/api/meta.py
mwdstdb/api/oilfield.py
mwdstdb/api/pad.py
mwdstdb/api/rpc.py
mwdstdb/api/run.py
mwdstdb/api/survey.py
mwdstdb/api/tasks.py
mwdstdb/api/toolcode.py
mwdstdb/api/user.py
mwdstdb/api/well.py
mwdstdb/api/workflow.py
mwdstdb/crud/__init__.py
mwdstdb/crud/borehole.py
mwdstdb/crud/client.py
mwdstdb/crud/common.py
mwdstdb/crud/control.py
mwdstdb/crud/etag.py
mwdstdb/crud/events.py
mwdstdb/crud/export.py
mwdstdb/crud/oilfield.py
mwdstdb/crud/pad.py
mwdstdb/crud/run.py
mwdstdb/crud/survey.py
mwdstdb/crud/well.py
mwdstdb/database.py
mwdstdb/main.py
mwdstdb/models/__init__.py
mwdstdb/models/bha.py
mwdstdb/models/borehole.py
mwdstdb/models/client.py
mwdstdb/models/correction.py
mwdstdb/models/dbmodel.py
mwdstdb/models/oilfield.py
mwdstdb/models/pad.py
mwdstdb/models/plan.py
mwdstdb/models/reference.py
mwdstdb/models/run.py
mwdstdb/models/section.py
mwdstdb/models/station.py
mwdstdb/models/survey.py
mwdstdb/models/tasks.py
mwdstdb/models/toolcode.py
mwdstdb/models/units.py
mwdstdb/models/user.py
mwdstdb/models/validation.py
mwdstdb/models/well.py
mwdstdb/rpc.py
mwdstdb/security.py
mwdstdb/tasks/__init__.py
mwdstdb/tasks/app.py
mwdstdb/tasks/corlv1.py
mwdstdb/tasks/corlv2.py
mwdstdb/tasks/corlv3.py
mwdstdb/tasks/correction.py
mwdstdb/tasks/update.py
mwdstdb/utils.py
mwdstdb-0.5.9.dist-info/LICENSE
mwdstdb-0.5.9.dist-info/WHEEL
mwdstdb-0.5.9.dist-info/METADATA
mwdstdb-0.5.9.dist-info/RECORD
